{ "retweet":[{"Time":"11/29/2013  20:56:00","user":"LuisMNunes","latitude":"48.86198","longitude":"2.3487","Retweet":"RT @lemondefr : Mort de Nelson #Mandela : comment la vie d'un homme a chang_ le destin de l'Afrique du Sud http://www.lemonde.fr/tiny/3437940/","Picture":"http://pbs.twimg.com/profile_images/378800000838789846/ce000654335b8f0032ee9386782b267a_normal.jpeg","Cluster":"3"} , {"Time":"11/29/2013  21:06:00","user":"MaximeGauin","latitude":"48.87819","longitude":"2.42589","Retweet":"RT @lemondefr : Mort de Nelson #Mandela : comment la vie d'un homme a chang_ le destin de l'Afrique du Sud http://www.lemonde.fr/tiny/3437940/","Picture":"http://pbs.twimg.com/profile_images/378800000240750292/78885c3e751ff05c3a57e6907accf29e_normal.jpeg","Cluster":"3"} , {"Time":"11/29/2013  21:16:00","user":"guytoo34","latitude":"44.41135","longitude":"0.2538","Retweet":"RT @lemondefr : Mort de Nelson #Mandela : comment la vie d'un homme a chang_ le destin de l'Afrique du Sud http://www.lemonde.fr/tiny/3437940/","Picture":"http://pbs.twimg.com/profile_images/378800000785536550/6dd645be6aa0afdd2b731aa053782329_normal.jpeg","Cluster":"3"} , {"Time":"11/29/2013  21:56:00","user":"JulienDelalande","latitude":"46.11241","longitude":"4.47255","Retweet":"RT @lemondefr : Mort de Nelson #Mandela : comment la vie d'un homme a chang_ le destin de l'Afrique du Sud http://www.lemonde.fr/tiny/3437940/","Picture":"http://pbs.twimg.com/profile_images/2308618289/hhcwftrxp8i7ko0vg6h9_normal.jpeg","Cluster":"3"} , {"Time":"11/29/2013  22:06:00","user":"jdaveti","latitude":"43.55764","longitude":"5.21962","Retweet":"RT @lemondefr : Mort de Nelson #Mandela : comment la vie d'un homme a chang_ le destin de l'Afrique du Sud http://www.lemonde.fr/tiny/3437940/","Picture":"http://pbs.twimg.com/profile_images/1592316500/kes_normal.jpeg","Cluster":"3"} , {"Time":"11/29/2013  22:24:00","user":"Zinakola","latitude":"43.46202","longitude":"1.57216","Retweet":"RT @lemondefr : Mort de Nelson #Mandela : comment la vie d'un homme a chang_ le destin de l'Afrique du Sud http://www.lemonde.fr/tiny/3437940/","Picture":"http://pbs.twimg.com/profile_images/378800000801558348/5e49f09aff564f0b5eaf1281ee0b17c8_normal.jpeg","Cluster":"3"}]}