{ "retweet":[{"Time":"6/20/13 23:09","user":"@andersonunes13","latitude":"-24.4711865733333","longitude":"-48.0464629183333","Retweet":"RT @outroangulo: Temos uma nova avenida em #portolegre, senhoras e senhores: Jo<cc><a3>o DEZENAS DE MILHARES DE PESSOAS<89><db>_ #vemprarua","Picture":"http://pbs.twimg.com/profile_images/378800000349312429/9a929828b122d369d0a73114c1457af1_normal.png","Cluster":"5"} , {"Time":"6/20/13 23:25","user":"@falhouedisse","latitude":"-30.047706","longitude":"-51.214418","Retweet":"RT @outroangulo: Temos uma nova avenida em #portolegre, senhoras e senhores: Jo<cc><a3>o DEZENAS DE MILHARES DE PESSOAS<89><db>_ #vemprarua","Picture":"http://pbs.twimg.com/profile_images/378800000548283790/faa8df88acbc5735220c5b86bbfd55af_normal.jpeg","Cluster":"5"}]}