{ "retweet":[{"Time":"6/21/13 0:06","user":"@TovinhoTenorio","latitude":"-17.2427446433333","longitude":"-43.1706711","Retweet":"RT @JOAOARAUJ0: Vi muita gente gritando por uma ideologia, mas tamb<cc><a9>m vi muita gente que s<cc>_ queria ter uma boa foto pra colocar no Facebook<89><db>_","Picture":"http://pbs.twimg.com/profile_images/1622519530/12142_1213906320882_1625546396_555153_2420207_n_normal.jpg","Cluster":"6"} , {"Time":"6/21/13 0:14","user":"@Prof_Sidiclei","latitude":"-23.55887552","longitude":"-46.65973457","Retweet":"RT @JOAOARAUJ0: Vi muita gente gritando por uma ideologia, mas tamb<cc><a9>m vi muita gente que s<cc>_ queria ter uma boa foto pra colocar no Facebook<89><db>_","Picture":"http://pbs.twimg.com/profile_images/3397714638/1287dc32ad041fec8626874a11ae3433_normal.jpeg","Cluster":"6"}]}