{ "retweet":[{"Time":"6/21/13 17:55","user":"@InformeRJO","latitude":"-22.3106846416667","longitude":"-45.7010001083333","Retweet":"RT @KingJeiLee: Os shoppings Nova Am<cc><a9>rica e Norte Shopping est<cc><a3>o fechados. #Manifesta<cc><a4><cc><b5>es #Brasil #RiodeJaneiro","Picture":"http://pbs.twimg.com/profile_images/2941600246/34e64abef7923349749599e009f09770_normal.jpeg","Cluster":"11"} , {"Time":"6/21/13 17:55","user":"@parada_s","latitude":"-16.0701873","longitude":"-47.9700695","Retweet":"RT @KingJeiLee: Os shoppings Nova Am<cc><a9>rica e Norte Shopping est<cc><a3>o fechados. #Manifesta<cc><a4><cc><b5>es #Brasil #RiodeJaneiro","Picture":"http://pbs.twimg.com/profile_images/2207859727/imagesCA5TTGTC_normal.jpg","Cluster":"11"}]}