{ "retweet":[{"Time":"11/25/2013  11:30:00","user":"joaogsmartins","latitude":"38.75","longitude":"-9.14","Retweet":"RT @Niltoncomedy: Mandei mail para a PEPSI internacional. Viva o Ronaldo! Viva a Coca-Cola ","Picture":"http://pbs.twimg.com/profile_images/378800000753881458/eedb852e81520e6c5f869bbe1b97b4b0_normal.jpeg","Cluster":"5"} , {"Time":"11/25/2013  09:30:00","user":"camilaseixass","latitude":"40.2","longitude":"-8.45","Retweet":"RT @Niltoncomedy: Mandei mail para a PEPSI internacional. Viva o Ronaldo! Viva a Coca-Cola ","Picture":"http://pbs.twimg.com/profile_images/378800000719076004/c0d74e9c02b7b2c163f92f6de5174ae8_normal.jpeg","Cluster":"5"} , {"Time":"11/25/2013  10:00:00","user":"TiagoFF46","latitude":"40.18","longitude":"-8.41","Retweet":"RT @Niltoncomedy: Mandei mail para a PEPSI internacional. Viva o Ronaldo! Viva a Coca-Cola ","Picture":"http://pbs.twimg.com/profile_images/378800000738364616/8be3a95bb4cd1e8141b8d44ce645a93c_normal.jpeg","Cluster":"5"} , {"Time":"11/25/2013  11:30:00","user":"daniela22alves","latitude":"40.21","longitude":"-8.41","Retweet":"RT @Niltoncomedy: Mandei mail para a PEPSI internacional. Viva o Ronaldo! Viva a Coca-Cola ","Picture":"http://pbs.twimg.com/profile_images/378800000688013557/d7320dd66842c0a80ba756aabcf422c9_normal.jpeg","Cluster":"5"}]}